ulrm/ULRM.py
ulrm/__init__.py
ulrm-1.0.1.data/data/LICENSE.txt
ulrm-1.0.1.data/data/README-cn.md
ulrm-1.0.1.data/data/README.md
ulrm-1.0.1.dist-info/LICENSE.txt
ulrm-1.0.1.dist-info/METADATA
ulrm-1.0.1.dist-info/WHEEL
ulrm-1.0.1.dist-info/top_level.txt
ulrm-1.0.1.dist-info/RECORD
